{
"type": "FeatureCollection",
"name": "gates",
"crs": { "type": "name", "properties": { "name": "urn:ogc:def:crs:OGC:1.3:CRS84" } },
"features": [
{"type":"Feature","properties":{"name":"合工大小北门","desc":"从这里进入校园，沿主路前往建筑与艺术学院","type":"gate"},"geometry":{"type":"Point","coordinates":[117.194936588212968,31.775293700520365]}},
{"type":"Feature","properties":{"name":"合工大大北门","desc":"从这里进入校园，沿主路前往建筑与艺术学院","type":"gate"},"geometry":{"type":"Point","coordinates":[117.199677759653056,31.776693474945546]}},
{"type":"Feature","properties":{"name":"合工大东南门","desc":null,"type":"gate"},"geometry":{"type":"Point","coordinates":[117.199217188713149,31.767789103440883]}},
{"type":"Feature","properties":{"name":"合工大西门","desc":null,"type":"gate"},"geometry":{"type":"Point","coordinates":[117.191667437619955,31.771442063150449]}}
]
}
